{
  "url": "https://runrepeat.com/brooks-catamount-3",
  "shoe_name": "Brooks Catamount 3",
  "brand": "Brooks",
  "total_score": "90",
  "pros": "Reduced weight from v2; Enhanced flexibility; Stable and secure ride; High-quality materials; Suitable for all footstrikes; Lightweight!; Fantastic Skyvault plate; Adaptable across various paces",
  "cons": "Poor upper ventilation; Tight fit for some; Limited grip in wet conditions",
  "RR_verdict": "The Brooks Catamount 3 brilliantly addresses some minor issues of its predecessor, blending comfort, stability, and lightness in a versatile trail shoe. We were thrilled by the improved upper—it's cozier and enhances the overall fit, though breathability and durability could be better. We highly recommend this model for runners looking for a shoe that offers excellent ground feel with good cushioning, providing a nimble yet stable performance across various terrains.",
  "awards": "Top pick in best Brooks trail running shoes, Top 18% in trail running shoes, Top 18% in Brooks running shoes",
  "external_ratings": "90 / 100 from 2,520 users | 88 / 100 from 13 experts",
  "review_date": "May 17, 2024",
  "terrain": "Trail",
  "arch": "Neutral",
  "use": "Hiking",
  "shoe_weight": "Men: 9.4 oz / 266g | Women: 8.4 oz / 238g",
  "toe_drop": "6 mm",
  "foot_height": "24 mm",
  "Audience score": "90 Great!",
  "Price": "$170",
  "Trail terrain": "Light, Moderate",
  "Arch support": "Neutral",
  "Weight lab": "9 oz / 255g, 9.4 oz / 266g",
  "Lightweight": "✗",
  "Drop lab": "6.8 mm, 6.0 mm",
  "Strike pattern": "Mid/forefoot",
  "Size": "True to size",
  "Midsole softness": "Balanced",
  "Difference in midsole softness in cold": "Normal",
  "Plate": "Rock plate",
  "Toebox durability": "Very bad",
  "Heel padding durability": "Good",
  "Outsole durability": "Decent",
  "Breathability": "Warm",
  "Width / fit": "Narrow",
  "Toebox width": "Wide",
  "Stiffness": "Moderate",
  "Difference in stiffness in cold": "Small",
  "Torsional rigidity": "Moderate",
  "Heel counter stiffness": "Flexible",
  "Lug depth": "2.9 mm",
  "Heel stack lab": "28.3 mm, 30.0 mm",
  "Forefoot lab": "21.5 mm, 24.0 mm",
  "Widths available": "Normal",
  "Season": "All seasons",
  "Removable insole": "✓",
  "Orthotic friendly": "✓",
  "Ranking": "#70",
  "RankingPercentile": "Top 22%",
  "Popularity": "#190",
  "PopularityPercentile": "Bottom 41%"
}