{
  "url": "https://runrepeat.com/hoka-kawana",
  "shoe_name": "Hoka Kawana",
  "brand": "HOKA",
  "total_score": "86",
  "pros": "Exceptionally comfortable; Secure fit; Smooth and stable ride; Protection hits the sweet spot; Above average durability; Versatile: running and gym; Best-looking Hoka so far",
  "cons": "Not particularly lively; Firmer than other Hokas; Needs some breaking in; Average-at-best grip",
  "RR_verdict": "In an attempt to merge the world of road running shoes with fitness sneakers, we found the Hoka Kawana to be versatile enough for gym workouts, CrossFit sessions, and daily short runs. It provides a lot of comfort, durability, and a stable ride to both experienced and beginner runners alike.",
  "awards": "",
  "external_ratings": "87 / 100 from 21,622 users | 84 / 100 from 20 experts",
  "review_date": "Oct 25, 2023",
  "terrain": "Road",
  "arch": "Neutral",
  "use": "Gym |, Jogging |, Treadmill |, Walking |, All-day wear",
  "shoe_weight": "Men: 10.7 oz / 303g | Women: 9.3 oz / 265g",
  "toe_drop": "5 mm",
  "foot_height": "25 mm",
  "Audience score": "86 Good!",
  "Price": "$140",
  "Pace": "Daily running",
  "Arch support": "Neutral",
  "Weight lab": "10.7 oz / 303g, 10.7 oz / 303g",
  "Drop lab": "5.7 mm, 5.0 mm",
  "Strike pattern": "Mid/forefoot",
  "Size": "True to size",
  "Midsole softness": "Balanced",
  "Difference in midsole softness in cold": "Normal",
  "Toebox durability": "Bad",
  "Heel padding durability": "-",
  "Outsole durability": "-",
  "Breathability": "Moderate",
  "Width / fit": "Narrow",
  "Toebox width": "Narrow",
  "Stiffness": "Moderate",
  "Difference in stiffness in cold": "Big",
  "Torsional rigidity": "Moderate",
  "Heel counter stiffness": "Moderate",
  "Rocker": "✓",
  "Heel lab": "32.8 mm, 30.0 mm",
  "Forefoot lab": "27.1 mm, 25.0 mm",
  "Widths available": "Normal",
  "Orthotic friendly": "✓",
  "Season": "All seasons",
  "Removable insole": "✓",
  "Ranking": "#337",
  "RankingPercentile": "Bottom 39%",
  "Popularity": "#173",
  "PopularityPercentile": "Top 32%"
}